{
    "key": "group_61f180ebc7b9d",
    "title": "Engaging Networks Multistep Lightbox",
    "fields": [
        {
            "key": "field_61f184a2c864f",
            "label": "Content & Styles",
            "name": "",
            "type": "tab",
            "instructions": "",
            "required": 0,
            "conditional_logic": 0,
            "wrapper": {
                "width": "",
                "class": "",
                "id": ""
            },
            "placement": "top",
            "endpoint": 0
        },
        {
            "key": "field_61f180fb94e9c",
            "label": "Engaging Networks Donation Page",
            "name": "engaging_networks_donation_page",
            "type": "url",
            "instructions": "",
            "required": 0,
            "conditional_logic": 0,
            "wrapper": {
                "width": "",
                "class": "",
                "id": ""
            },
            "default_value": "",
            "placeholder": ""
        },
        {
            "key": "field_61f181cf13df7",
            "label": "Image",
            "name": "engrid_image",
            "type": "image",
            "instructions": "Main Image of the Lightbox.",
            "required": 0,
            "conditional_logic": 0,
            "wrapper": {
                "width": "50",
                "class": "",
                "id": ""
            },
            "return_format": "url",
            "preview_size": "medium",
            "library": "all",
            "min_width": "",
            "min_height": "",
            "min_size": "",
            "max_width": "",
            "max_height": "",
            "max_size": "",
            "mime_types": ""
        },
        {
            "key": "field_61f1822313df8",
            "label": "Logo",
            "name": "engrid_logo",
            "type": "image",
            "instructions": "Logo Image Used on the center of the Lightbox. On mobile, it will be scaled down and moved to the top.",
            "required": 0,
            "conditional_logic": 0,
            "wrapper": {
                "width": "50",
                "class": "",
                "id": ""
            },
            "return_format": "url",
            "preview_size": "medium",
            "library": "all",
            "min_width": "",
            "min_height": "",
            "min_size": "",
            "max_width": "",
            "max_height": "",
            "max_size": "",
            "mime_types": ""
        },
        {
            "key": "field_61f1829913df9",
            "label": "Title",
            "name": "engrid_title",
            "type": "text",
            "instructions": "Title of the Lightbox.",
            "required": 0,
            "conditional_logic": 0,
            "wrapper": {
                "width": "",
                "class": "",
                "id": ""
            },
            "default_value": "",
            "placeholder": "",
            "prepend": "",
            "append": "",
            "maxlength": ""
        },
        {
            "key": "field_61f182a213dfa",
            "label": "Paragraph",
            "name": "engrid_paragraph",
            "type": "textarea",
            "instructions": "Content of the Lightbox.",
            "required": 0,
            "conditional_logic": 0,
            "wrapper": {
                "width": "",
                "class": "",
                "id": ""
            },
            "default_value": "",
            "placeholder": "",
            "maxlength": "",
            "rows": "",
            "new_lines": ""
        },
        {
            "key": "field_61f1837e13dfe",
            "label": "Footer",
            "name": "engrid_footer",
            "type": "textarea",
            "instructions": "Content of the footer.",
            "required": 0,
            "conditional_logic": 0,
            "wrapper": {
                "width": "",
                "class": "",
                "id": ""
            },
            "default_value": "",
            "placeholder": "",
            "maxlength": "",
            "rows": "",
            "new_lines": ""
        },
        {
            "key": "field_61f182b413dfb",
            "label": "BG Color",
            "name": "engrid_bg_color",
            "type": "color_picker",
            "instructions": "HEX color of the left column background.",
            "required": 0,
            "conditional_logic": 0,
            "wrapper": {
                "width": "33",
                "class": "",
                "id": ""
            },
            "default_value": "#000000",
            "enable_opacity": 0,
            "return_format": "string"
        },
        {
            "key": "field_61f1833c13dfc",
            "label": "Text Color",
            "name": "engrid_text_color",
            "type": "color_picker",
            "instructions": "HEX color of the left column text.",
            "required": 0,
            "conditional_logic": 0,
            "wrapper": {
                "width": "33",
                "class": "",
                "id": ""
            },
            "default_value": "#FFFFFF",
            "enable_opacity": 0,
            "return_format": "string"
        },
        {
            "key": "field_61f1835413dfd",
            "label": "Form Color",
            "name": "engrid_form_color",
            "type": "color_picker",
            "instructions": "HEX color for the form theme.",
            "required": 0,
            "conditional_logic": 0,
            "wrapper": {
                "width": "33",
                "class": "",
                "id": ""
            },
            "default_value": "#000000",
            "enable_opacity": 0,
            "return_format": "string"
        },
        {
            "key": "field_61f184e1c8650",
            "label": "Trigger Options",
            "name": "",
            "type": "tab",
            "instructions": "",
            "required": 0,
            "conditional_logic": 0,
            "wrapper": {
                "width": "",
                "class": "",
                "id": ""
            },
            "placement": "top",
            "endpoint": 0
        },
        {
            "key": "field_61f18500c8651",
            "label": "Show On",
            "name": "engrid_show_on",
            "type": "relationship",
            "instructions": "",
            "required": 0,
            "conditional_logic": 0,
            "wrapper": {
                "width": "",
                "class": "",
                "id": ""
            },
            "post_type": "",
            "taxonomy": "",
            "filters": [
                "search",
                "post_type",
                "taxonomy"
            ],
            "elements": [
                "featured_image"
            ],
            "min": "",
            "max": "",
            "return_format": "id"
        },
        {
            "key": "field_61f185c0c8654",
            "label": "Hide On",
            "name": "engrid_hide_on",
            "type": "relationship",
            "instructions": "",
            "required": 0,
            "conditional_logic": 0,
            "wrapper": {
                "width": "",
                "class": "",
                "id": ""
            },
            "post_type": "",
            "taxonomy": "",
            "filters": [
                "search",
                "post_type",
                "taxonomy"
            ],
            "elements": [
                "featured_image"
            ],
            "min": "",
            "max": "",
            "return_format": "id"
        },
        {
            "key": "field_61f1856cc8652",
            "label": "Start Date",
            "name": "engrid_start_date",
            "type": "date_picker",
            "instructions": "",
            "required": 0,
            "conditional_logic": 0,
            "wrapper": {
                "width": "50",
                "class": "",
                "id": ""
            },
            "display_format": "d\/m\/Y",
            "return_format": "d\/m\/Y",
            "first_day": 1
        },
        {
            "key": "field_61f185aac8653",
            "label": "End Date",
            "name": "engrid_end_date",
            "type": "date_picker",
            "instructions": "",
            "required": 0,
            "conditional_logic": 0,
            "wrapper": {
                "width": "50",
                "class": "",
                "id": ""
            },
            "display_format": "d\/m\/Y",
            "return_format": "d\/m\/Y",
            "first_day": 1
        },
        {
            "key": "field_61f1839713dff",
            "label": "Cookie Hours",
            "name": "cookie_hours",
            "type": "number",
            "instructions": "Number of hours to not auto open the lightbox after the user closes it.",
            "required": 0,
            "conditional_logic": 0,
            "wrapper": {
                "width": "",
                "class": "",
                "id": ""
            },
            "default_value": 24,
            "placeholder": "",
            "prepend": "",
            "append": "",
            "min": "",
            "max": "",
            "step": 1
        }
    ],
    "location": [
        [
            {
                "param": "options_page",
                "operator": "==",
                "value": "multistep-lightbox"
            }
        ]
    ],
    "menu_order": 0,
    "position": "normal",
    "style": "default",
    "label_placement": "top",
    "instruction_placement": "label",
    "hide_on_screen": "",
    "active": true,
    "description": "",
    "show_in_rest": 0,
    "modified": 1643218418
}